hash_fixture.py
hash_fixture-0.0.1.dist-info/licenses/LICENSES/MIT.txt
hash_fixture-0.0.1.dist-info/METADATA
hash_fixture-0.0.1.dist-info/WHEEL
hash_fixture-0.0.1.dist-info/top_level.txt
hash_fixture-0.0.1.dist-info/zip-safe
hash_fixture-0.0.1.dist-info/RECORD
