Metadata-Version: 2.4
Name: hash-fixture
Version: 0.0.1
Summary: Produce lines of reproducible test fixture by repeated hashing
Home-page: https://github.com/moreati/hash-fixture/
Author: Alex Willmer
Author-email: alex@moreati.org.uk
License: MIT
Classifier: Environment :: Console
Classifier: Development Status :: 3 - Alpha
Classifier: Intended Audience :: Developers
Classifier: Operating System :: OS Independent
Classifier: Programming Language :: Python :: 2.7
Classifier: Programming Language :: Python :: 3.8
Classifier: Programming Language :: Python :: 3.9
Classifier: Programming Language :: Python :: 3.10
Classifier: Programming Language :: Python :: 3.11
Classifier: Programming Language :: Python :: 3.12
Classifier: Programming Language :: Python :: 3.13
Classifier: Programming Language :: Python :: 3.14
Classifier: Typing :: Typed
Requires-Python: !=3.0,!=3.1,!=3.2,!=3.3,!=3.4,!=3.5,>=2.7
License-File: LICENSES/MIT.txt
Dynamic: license-file
